cubicweb_preview/__init__.py
cubicweb_preview/__pkginfo__.py
cubicweb_preview/hooks.py
cubicweb_preview/site_cubicweb.py
cubicweb_preview/uiprops.py
cubicweb_preview/utils.py
cubicweb_preview/data/cubes.preview.js
cubicweb_preview/data/preview.png
cubicweb_preview/entities/__init__.py
cubicweb_preview/entities/adapters.py
cubicweb_preview/i18n/en.po
cubicweb_preview/i18n/es.po
cubicweb_preview/i18n/fr.po
cubicweb_preview/views/__init__.py
cubicweb_preview/views/controllers.py
cubicweb_preview/views/forms.py
cubicweb_preview/views/templates.py
cubicweb_preview/wdoc/ChangeLog_en
cubicweb_preview/wdoc/preview_en.rst
cubicweb_preview/wdoc/toc.xml
cubicweb_preview/wdoc/todo_en.rst
cubicweb_preview-3.1.0.dist-info/METADATA
cubicweb_preview-3.1.0.dist-info/WHEEL
cubicweb_preview-3.1.0.dist-info/entry_points.txt
cubicweb_preview-3.1.0.dist-info/top_level.txt
cubicweb_preview-3.1.0.dist-info/RECORD
